nginxproxymanager/__init__.py
nginxproxymanager/client.py
nginxproxymanager/nginx.py
nginxproxymanager/types/__init__.py
nginxproxymanager/types/proxy_hosts.py
nginxproxymanager/types/root.py
nginxproxymanager/utils.py
nginxproxymanager-0.1.0.dist-info/LICENSE
nginxproxymanager-0.1.0.dist-info/WHEEL
nginxproxymanager-0.1.0.dist-info/METADATA
nginxproxymanager-0.1.0.dist-info/RECORD
