Metadata-Version: 2.1
Name: nginxproxymanager
Version: 0.1.0
Summary: 
Home-page: https://github.com/regulad/nginxproxymanager-py
License: GPLv3
Author: Parker Wahle
Author-email: regulad@regulad.xyz
Requires-Python: >=3.10,<4.0
Classifier: License :: Other/Proprietary License
Classifier: Programming Language :: Python :: 3
Classifier: Programming Language :: Python :: 3.10
Requires-Dist: aiohttp (>=3.8.3,<4.0.0)
Requires-Dist: requests (>=2.28.1,<3.0.0)
Project-URL: Repository, https://github.com/regulad/nginxproxymanager-py
